Workbook

Sheet Datos
A1: firm_id | B1: firm_name | C1: sector | D1: reporting_period | E1: revenue_reported_mm | F1: revenue_growth_pct | G1: operating_expenses_reported_mm | H1: ebitda_reported_mm | I1: ebitda_margin_change_pp | J1: cfo_reported_mm | K1: capex_total_reported_mm | L1: capex_growth_pct | M1: maintenance_capex_reported_mm | N1: growth_capex_reported_mm | O1: adjusted_ebitda_reported_mm | P1: interest_expense_reported_mm | Q1: cash_taxes_reported_mm | R1: net_income_reported_mm | S1: dividends_mm | T1: debt_avg_mm | U1: debt_end_reported_mm | V1: total_assets_reported_mm | W1: cash_reported_mm | X1: accounts_receivable_reported_mm | Y1: inventory_reported_mm | Z1: npl_reported_mm | AA1: npl_growth_pct | AB1: provision_reported_mm | AC1: loan_loss_reserve_reported_mm | AD1: coverage_change_pp | AE1: ebitda_margin_pct | AF1: cfo_margin_pct | AG1: capex_intensity_pct | AH1: maintenance_capex_share_pct | AI1: fcf_reported_mm | AJ1: distributable_cash_flow_reported_mm | AK1: dcf_fcf_gap_mm | AL1: dividend_coverage_dcf_x | AM1: dividend_coverage_fcf_x | AN1: debt_end_to_avg_x | AO1: leverage_avg_x | AP1: leverage_reported_x | AQ1: credit_loss_coverage_reported_x | AR1: cfo_to_ebitda_reported_x | AS1: assets_to_revenue_x
A2: F0902 | B2: Empresa Sintética 0902 | C2: Consumer | D2: FY2025 | E2: 450.10696 | F2: 0.096127746 | G2: 352.61213 | H2: 97.494822 | I2: 0.0004008724 | J2: 71.418682 | K2: 28.80452 | L2: -0.11450778 | M2: 17.720964 | N2: 11.083555 | O2: 97.669655 | P2: 16.106182 | Q2: 11.74695 | R2: 60.462556 | S2: 10.58107 | T2: 226.29612 | U2: 235.06306 | V2: 808.92015 | W2: 96.533618 | X2: 45.797524 | Y2: 46.451263 | Z2: 0 | AA2: 0 | AB2: 0 | AC2: 0 | AD2: 0 | AE2: =IF(E2=0,"",H2/E2) -> 0.21660368 | AF2: =IF(E2=0,"",J2/E2) -> 0.15867047 | AG2: =IF(E2=0,"",K2/E2) -> 0.063994833 | AH2: =IF(K2=0,"",M2/K2) -> 0.61521472 | AI2: =J2-K2 -> 42.614162 | AJ2: =O2-P2-M2-Q2 -> 52.095558 | AK2: =AJ2-AI2 -> 9.4813961 | AL2: =IF(S2=0,"",AJ2/S2) -> 4.9234677 | AM2: =IF(S2=0,"",AI2/S2) -> 4.0273961 | AN2: =IF(T2=0,"",U2/T2) -> 1.038741 | AO2: =IF(H2=0,"",T2/H2) -> 2.3211091 | AP2: =IF(H2=0,"",U2/H2) -> 2.4110312 | AQ2: =IF(Z2=0,"",AC2/Z2) | AR2: =IF(H2=0,"",J2/H2) -> 0.73253821 | AS2: =IF(E2=0,"",V2/E2) -> 1.7971732
A3: F0433 | B3: Empresa Sintética 0433 | C3: Technology | D3: FY2025 | E3: 191.0037 | F3: -0.0080269671 | G3: 132.74599 | H3: 58.257713 | I3: 0.0086133312 | J3: 38.250478 | K3: 14.858979 | L3: 0.12241776 | M3: 6.9324024 | N3: 7.9265765 | O3: 59.798605 | P3: 6.7024177 | Q3: 8.0239461 | R3: 40.149247 | S3: 9.5492349 | T3: 124.05618 | U3: 118.54071 | V3: 178.89785 | W3: 19.937815 | X3: 29.806876 | Y3: 0.8090285 | Z3: 0 | AA3: 0 | AB3: 0 | AC3: 0 | AD3: 0 | AE3: =IF(E3=0,"",H3/E3) -> 0.3050083 | AF3: =IF(E3=0,"",J3/E3) -> 0.20026041 | AG3: =IF(E3=0,"",K3/E3) -> 0.077794195 | AH3: =IF(K3=0,"",M3/K3) -> 0.46654635 | AI3: =J3-K3 -> 23.391499 | AJ3: =O3-P3-M3-Q3 -> 38.139839 | AK3: =AJ3-AI3 -> 14.748339 | AL3: =IF(S3=0,"",AJ3/S3) -> 3.9940203 | AM3: =IF(S3=0,"",AI3/S3) -> 2.4495679 | AN3: =IF(T3=0,"",U3/T3) -> 0.95554056 | AO3: =IF(H3=0,"",T3/H3) -> 2.1294379 | AP3: =IF(H3=0,"",U3/H3) -> 2.0347643 | AQ3: =IF(Z3=0,"",AC3/Z3) | AR3: =IF(H3=0,"",J3/H3) -> 0.65657363 | AS3: =IF(E3=0,"",V3/E3) -> 0.93661981
A4: F0060 | B4: Empresa Sintética 0060 | C4: Energy | D4: FY2025 | E4: 212.5818 | F4: -0.039645264 | G4: 153.41738 | H4: 59.164422 | I4: 0.012086317 | J4: 48.388364 | K4: 48.902255 | L4: -0.013380416 | M4: 28.152278 | N4: 20.749977 | O4: 60.547773 | P4: 14.045623 | Q4: 6.0174549 | R4: 26.29302 | S4: 6.338935 | T4: 155.01687 | U4: 150.17006 | V4: 492.72778 | W4: 60.548701 | X4: 32.38628 | Y4: 23.60516 | Z4: 0 | AA4: 0 | AB4: 0 | AC4: 0 | AD4: 0 | AE4: =IF(E4=0,"",H4/E4) -> 0.27831367 | AF4: =IF(E4=0,"",J4/E4) -> 0.22762233 | AG4: =IF(E4=0,"",K4/E4) -> 0.23003971 | AH4: =IF(K4=0,"",M4/K4) -> 0.57568466 | AI4: =J4-K4 -> -0.51389185 | AJ4: =O4-P4-M4-Q4 -> 12.332417 | AK4: =AJ4-AI4 -> 12.846309 | AL4: =IF(S4=0,"",AJ4/S4) -> 1.945503 | AM4: =IF(S4=0,"",AI4/S4) -> -0.081069116 | AN4: =IF(T4=0,"",U4/T4) -> 0.96873368 | AO4: =IF(H4=0,"",T4/H4) -> 2.6201028 | AP4: =IF(H4=0,"",U4/H4) -> 2.5381818 | AQ4: =IF(Z4=0,"",AC4/Z4) | AR4: =IF(H4=0,"",J4/H4) -> 0.81786253 | AS4: =IF(E4=0,"",V4/E4) -> 2.3178267
A5: F0257 | B5: Empresa Sintética 0257 | C5: Financials | D5: FY2025 | E5: 206.76323 | F5: 0.012685321 | G5: 139.49388 | H5: 67.269346 | I5: 0.002957823 | J5: 39.379762 | K5: 7.1389647 | L5: 0.034518804 | M5: 3.9733785 | N5: 3.1655862 | O5: 69.633977 | P5: 7.4702903 | Q5: 14.153827 | R5: 41.708684 | S5: 8.1839714 | T5: 75.911654 | U5: 72.8591 | V5: 908.97315 | W5: 110.26459 | X5: 5.7556012 | Y5: 0.33975663 | Z5: 22.205528 | AA5: -0.020940112 | AB5: 2.2679265 | AC5: 8.0658272 | AD5: 0.031536919 | AE5: =IF(E5=0,"",H5/E5) -> 0.32534482 | AF5: =IF(E5=0,"",J5/E5) -> 0.19045825 | AG5: =IF(E5=0,"",K5/E5) -> 0.034527245 | AH5: =IF(K5=0,"",M5/K5) -> 0.55657629 | AI5: =J5-K5 -> 32.240798 | AJ5: =O5-P5-M5-Q5 -> 44.036482 | AK5: =AJ5-AI5 -> 11.795684 | AL5: =IF(S5=0,"",AJ5/S5) -> 5.3808207 | AM5: =IF(S5=0,"",AI5/S5) -> 3.9395052 | AN5: =IF(T5=0,"",U5/T5) -> 0.95978808 | AO5: =IF(H5=0,"",T5/H5) -> 1.1284732 | AP5: =IF(H5=0,"",U5/H5) -> 1.0830951 | AQ5: =IF(Z5=0,"",AC5/Z5) -> 0.3632351 | AR5: =IF(H5=0,"",J5/H5) -> 0.58540427 | AS5: =IF(E5=0,"",V5/E5) -> 4.3962031
A6: F0057 | B6: Empresa Sintética 0057 | C6: Energy | D6: FY2025 | E6: 96.633886 | F6: 0.041337894 | G6: 72.479557 | H6: 24.154329 | I6: 0.002733216 | J6: 20.172502 | K6: 18.916024 | L6: 0.16086011 | M6: 12.701556 | N6: 6.2144685 | O6: 24.435145 | P6: 2.5124765 | Q6: 3.1638525 | R6: 12.822123 | S6: 1.9218553 | T6: 37.862366 | U6: 34.053565 | V6: 253.80377 | W6: 26.656851 | X6: 14.416919 | Y6: 8.2258426 | Z6: 0 | AA6: 0 | AB6: 0 | AC6: 0 | AD6: 0 | AE6: =IF(E6=0,"",H6/E6) -> 0.24995713 | AF6: =IF(E6=0,"",J6/E6) -> 0.20875184 | AG6: =IF(E6=0,"",K6/E6) -> 0.19574939 | AH6: =IF(K6=0,"",M6/K6) -> 0.67147069 | AI6: =J6-K6 -> 1.2564774 | AJ6: =O6-P6-M6-Q6 -> 6.0572603 | AK6: =AJ6-AI6 -> 4.8007828 | AL6: =IF(S6=0,"",AJ6/S6) -> 3.1517774 | AM6: =IF(S6=0,"",AI6/S6) -> 0.65378357 | AN6: =IF(T6=0,"",U6/T6) -> 0.89940404 | AO6: =IF(H6=0,"",T6/H6) -> 1.5675189 | AP6: =IF(H6=0,"",U6/H6) -> 1.4098328 | AQ6: =IF(Z6=0,"",AC6/Z6) | AR6: =IF(H6=0,"",J6/H6) -> 0.83515059 | AS6: =IF(E6=0,"",V6/E6) -> 2.6264469
A7: F0657 | B7: Empresa Sintética 0657 | C7: Industrials | D7: FY2025 | E7: 409.03939 | F7: 0.054423363 | G7: 329.50385 | H7: 79.535548 | I7: 0.00095494544 | J7: 45.933482 | K7: 43.485064 | L7: 0.15695072 | M7: 29.841245 | N7: 13.643819 | O7: 81.951529 | P7: 32.55941 | Q7: 7.0245135 | R7: 27.509211 | S7: 5.4040513 | T7: 323.37083 | U7: 343.30915 | V7: 624.25424 | W7: 32.780575 | X7: 66.556854 | Y7: 94.743717 | Z7: 0 | AA7: 0 | AB7: 0 | AC7: 0 | AD7: 0 | AE7: =IF(E7=0,"",H7/E7) -> 0.19444471 | AF7: =IF(E7=0,"",J7/E7) -> 0.11229599 | AG7: =IF(E7=0,"",K7/E7) -> 0.10631021 | AH7: =IF(K7=0,"",M7/K7) -> 0.68624126 | AI7: =J7-K7 -> 2.4484176 | AJ7: =O7-P7-M7-Q7 -> 12.52636 | AK7: =AJ7-AI7 -> 10.077943 | AL7: =IF(S7=0,"",AJ7/S7) -> 2.3179573 | AM7: =IF(S7=0,"",AI7/S7) -> 0.45307075 | AN7: =IF(T7=0,"",U7/T7) -> 1.0616577 | AO7: =IF(H7=0,"",T7/H7) -> 4.0657397 | AP7: =IF(H7=0,"",U7/H7) -> 4.316424 | AQ7: =IF(Z7=0,"",AC7/Z7) | AR7: =IF(H7=0,"",J7/H7) -> 0.57752141 | AS7: =IF(E7=0,"",V7/E7) -> 1.526147
A8: F0773 | B8: Empresa Sintética 0773 | C8: Industrials | D8: FY2025 | E8: 276.61955 | F8: 0.010550693 | G8: 205.98892 | H8: 70.63063 | I8: 0.012667606 | J8: 54.704974 | K8: 20.699448 | L8: -0.071192434 | M8: 14.436327 | N8: 6.263121 | O8: 72.974654 | P8: 7.9766426 | Q8: 10.722103 | R8: 47.607613 | S8: 3.8580774 | T8: 132.15007 | U8: 135.8001 | V8: 430.75454 | W8: 20.978989 | X8: 50.514484 | Y8: 34.723453 | Z8: 0 | AA8: 0 | AB8: 0 | AC8: 0 | AD8: 0 | AE8: =IF(E8=0,"",H8/E8) -> 0.25533492 | AF8: =IF(E8=0,"",J8/E8) -> 0.1977625 | AG8: =IF(E8=0,"",K8/E8) -> 0.074830025 | AH8: =IF(K8=0,"",M8/K8) -> 0.6974257 | AI8: =J8-K8 -> 34.005526 | AJ8: =O8-P8-M8-Q8 -> 39.839582 | AK8: =AJ8-AI8 -> 5.8340561 | AL8: =IF(S8=0,"",AJ8/S8) -> 10.326279 | AM8: =IF(S8=0,"",AI8/S8) -> 8.8141119 | AN8: =IF(T8=0,"",U8/T8) -> 1.0276203 | AO8: =IF(H8=0,"",T8/H8) -> 1.8710024 | AP8: =IF(H8=0,"",U8/H8) -> 1.92268 | AQ8: =IF(Z8=0,"",AC8/Z8) | AR8: =IF(H8=0,"",J8/H8) -> 0.77452196 | AS8: =IF(E8=0,"",V8/E8) -> 1.5572093
A9: F0574 | B9: Empresa Sintética 0574 | C9: Technology | D9: FY2025 | E9: 112.7159 | F9: -0.033665815 | G9: 93.562167 | H9: 19.153728 | I9: -0.027072946 | J9: 15.766308 | K9: 10.783648 | L9: -0.041848772 | M9: 2.7520405 | N9: 8.0316078 | O9: 20.712754 | P9: 3.0112735 | Q9: 1.5772404 | R9: 11.991209 | S9: 0.85013651 | T9: 24.76065 | U9: 25.053864 | V9: 189.61497 | W9: 19.029215 | X9: 25.707226 | Y9: 2.281561 | Z9: 0 | AA9: 0 | AB9: 0 | AC9: 0 | AD9: 0 | AE9: =IF(E9=0,"",H9/E9) -> 0.16992926 | AF9: =IF(E9=0,"",J9/E9) -> 0.13987653 | AG9: =IF(E9=0,"",K9/E9) -> 0.095671052 | AH9: =IF(K9=0,"",M9/K9) -> 0.25520496 | AI9: =J9-K9 -> 4.9826597 | AJ9: =O9-P9-M9-Q9 -> 13.3722 | AK9: =AJ9-AI9 -> 8.3895399 | AL9: =IF(S9=0,"",AJ9/S9) -> 15.729473 | AM9: =IF(S9=0,"",AI9/S9) -> 5.8610113 | AN9: =IF(T9=0,"",U9/T9) -> 1.0118419 | AO9: =IF(H9=0,"",T9/H9) -> 1.2927326 | AP9: =IF(H9=0,"",U9/H9) -> 1.3080411 | AQ9: =IF(Z9=0,"",AC9/Z9) | AR9: =IF(H9=0,"",J9/H9) -> 0.82314564 | AS9: =IF(E9=0,"",V9/E9) -> 1.6822381
A10: F0438 | B10: Empresa Sintética 0438 | C10: Technology | D10: FY2025 | E10: 131.99086 | F10: 0.015603987 | G10: 106.48893 | H10: 25.501931 | I10: 0.010874475 | J10: 16.380991 | K10: 4.3440797 | L10: -0.099613091 | M10: 2.1269933 | N10: 2.2170864 | O10: 26.87386 | P10: 3.0094966 | Q10: 4.4910471 | R10: 17.005806 | S10: 2.8673021 | T10: 42.875912 | U10: 43.64344 | V10: 188.12826 | W10: 13.991141 | X10: 19.877222 | Y10: 3.1477833 | Z10: 0 | AA10: 0 | AB10: 0 | AC10: 0 | AD10: 0 | AE10: =IF(E10=0,"",H10/E10) -> 0.19320982 | AF10: =IF(E10=0,"",J10/E10) -> 0.12410701 | AG10: =IF(E10=0,"",K10/E10) -> 0.032911973 | AH10: =IF(K10=0,"",M10/K10) -> 0.48963035 | AI10: =J10-K10 -> 12.036912 | AJ10: =O10-P10-M10-Q10 -> 17.246323 | AK10: =AJ10-AI10 -> 5.2094113 | AL10: =IF(S10=0,"",AJ10/S10) -> 6.0148259 | AM10: =IF(S10=0,"",AI10/S10) -> 4.1979922 | AN10: =IF(T10=0,"",U10/T10) -> 1.0179011 | AO10: =IF(H10=0,"",T10/H10) -> 1.681281 | AP10: =IF(H10=0,"",U10/H10) -> 1.7113779 | AQ10: =IF(Z10=0,"",AC10/Z10) | AR10: =IF(H10=0,"",J10/H10) -> 0.64234319 | AS10: =IF(E10=0,"",V10/E10) -> 1.4253127
A11: F0375 | B11: Empresa Sintética 0375 | C11: Financials | D11: FY2025 | E11: 92.276374 | F11: 0.053450957 | G11: 59.81044 | H11: 32.465934 | I11: -0.011156675 | J11: 20.846569 | K11: 1.7347856 | L11: -0.061247042 | M11: 1.0400713 | N11: 0.69471422 | O11: 33.870802 | P11: 10.7739 | Q11: 3.5676504 | R11: 16.71703 | S11: 3.437914 | T11: 103.86383 | U11: 99.160391 | V11: 562.98162 | W11: 24.422333 | X11: 4.9868026 | Y11: 0.22984411 | Z11: 6.5775478 | AA11: -0.036070327 | AB11: 0.82668784 | AC11: 2.5732554 | AD11: 0.035552293 | AE11: =IF(E11=0,"",H11/E11) -> 0.35183365 | AF11: =IF(E11=0,"",J11/E11) -> 0.22591448 | AG11: =IF(E11=0,"",K11/E11) -> 0.018799889 | AH11: =IF(K11=0,"",M11/K11) -> 0.59953885 | AI11: =J11-K11 -> 19.111783 | AJ11: =O11-P11-M11-Q11 -> 18.489181 | AK11: =AJ11-AI11 -> -0.6226025 | AL11: =IF(S11=0,"",AJ11/S11) -> 5.3780231 | AM11: =IF(S11=0,"",AI11/S11) -> 5.559122 | AN11: =IF(T11=0,"",U11/T11) -> 0.95471534 | AO11: =IF(H11=0,"",T11/H11) -> 3.1991635 | AP11: =IF(H11=0,"",U11/H11) -> 3.0542904 | AQ11: =IF(Z11=0,"",AC11/Z11) -> 0.39121805 | AR11: =IF(H11=0,"",J11/H11) -> 0.64210593 | AS11: =IF(E11=0,"",V11/E11) -> 6.1010375
A12: F0296 | B12: Empresa Sintética 0296 | C12: Financials | D12: FY2025 | E12: 193.46273 | F12: 0.035027137 | G12: 117.66533 | H12: 75.797398 | I12: 0.013396099 | J12: 58.030875 | K12: 3.3196176 | L12: -0.040840993 | M12: 1.747148 | N12: 1.5724696 | O12: 78.035843 | P12: 13.473453 | Q12: 9.9290619 | R12: 50.045595 | S12: 14.477341 | T12: 140.71616 | U12: 148.32605 | V12: 908.95765 | W12: 30.120094 | X12: 8.1505035 | Y12: 1.6154423 | Z12: 22.638743 | AA12: 0.13813656 | AB12: 1.5651329 | AC12: 7.3746544 | AD12: -0.040824608 | AE12: =IF(E12=0,"",H12/E12) -> 0.39179328 | AF12: =IF(E12=0,"",J12/E12) -> 0.29995894 | AG12: =IF(E12=0,"",K12/E12) -> 0.017158951 | AH12: =IF(K12=0,"",M12/K12) -> 0.52631001 | AI12: =J12-K12 -> 54.711258 | AJ12: =O12-P12-M12-Q12 -> 52.886181 | AK12: =AJ12-AI12 -> -1.8250773 | AL12: =IF(S12=0,"",AJ12/S12) -> 3.6530315 | AM12: =IF(S12=0,"",AI12/S12) -> 3.7790959 | AN12: =IF(T12=0,"",U12/T12) -> 1.0540797 | AO12: =IF(H12=0,"",T12/H12) -> 1.8564775 | AP12: =IF(H12=0,"",U12/H12) -> 1.9568752 | AQ12: =IF(Z12=0,"",AC12/Z12) -> 0.32575371 | AR12: =IF(H12=0,"",J12/H12) -> 0.76560511 | AS12: =IF(E12=0,"",V12/E12) -> 4.6983605
A13: F0312 | B13: Empresa Sintética 0312 | C13: Financials | D13: FY2025 | E13: 277.08286 | F13: -0.13213701 | G13: 224.84512 | H13: 52.237747 | I13: -0.033885648 | J13: 29.975624 | K13: 4.0415801 | L13: -0.10641888 | M13: 1.7305723 | N13: 2.3110078 | O13: 55.33941 | P13: 18.193068 | Q13: 4.5556059 | R13: 22.11227 | S13: 3.6127944 | T13: 197.70045 | U13: 155.73123 | V13: 1035.8669 | W13: 84.300617 | X13: 17.279149 | Y13: 0.81892061 | Z13: 63.753516 | AA13: 0.30819427 | AB13: 6.2163523 | AC13: 22.581637 | AD13: 0.038780063 | AE13: =IF(E13=0,"",H13/E13) -> 0.18852753 | AF13: =IF(E13=0,"",J13/E13) -> 0.10818289 | AG13: =IF(E13=0,"",K13/E13) -> 0.014586179 | AH13: =IF(K13=0,"",M13/K13) -> 0.42819201 | AI13: =J13-K13 -> 25.934044 | AJ13: =O13-P13-M13-Q13 -> 30.860164 | AK13: =AJ13-AI13 -> 4.92612 | AL13: =IF(S13=0,"",AJ13/S13) -> 8.5419096 | AM13: =IF(S13=0,"",AI13/S13) -> 7.1783889 | AN13: =IF(T13=0,"",U13/T13) -> 0.78771307 | AO13: =IF(H13=0,"",T13/H13) -> 3.7846281 | AP13: =IF(H13=0,"",U13/H13) -> 2.981201 | AQ13: =IF(Z13=0,"",AC13/Z13) -> 0.35420222 | AR13: =IF(H13=0,"",J13/H13) -> 0.57383071 | AS13: =IF(E13=0,"",V13/E13) -> 3.7384734
... A1001: F0297 | B1001: Empresa Sintética 0297 | C1001: Financials | D1001: FY2025 | E1001: 140.88299 | F1001: 0.030418538 | G1001: 83.082863 | H1001: 57.800126 | I1001: -0.0091775604 | J1001: 53.928279 | K1001: 4.0051314 | L1001: 0.0047954725 | M1001: 2.51058 | N1001: 1.4945514 | O1001: 58.710886 | P1001: 7.9173758 | Q1001: 11.963735 | R1001: 35.389453 | S1001: 3.9196806 | T1001: 123.59335 | U1001: 123.17715 | V1001: 727.87315 | W1001: 41.947005 | X1001: 5.9551082 | Y1001: 0.38488894 | Z1001: 10.855673 | AA1001: 0.11784653 | AB1001: 1.1982419 | AC1001: 5.2584172 | AD1001: -0.022150364 | AE1001: =IF(E1001=0,"",H1001/E1001) -> 0.41027044 | AF1001: =IF(E1001=0,"",J1001/E1001) -> 0.38278773 | AG1001: =IF(E1001=0,"",K1001/E1001) -> 0.028428779 | AH1001: =IF(K1001=0,"",M1001/K1001) -> 0.62684085 | AI1001: =J1001-K1001 -> 49.923148 | AJ1001: =O1001-P1001-M1001-Q1001 -> 36.319196 | AK1001: =AJ1001-AI1001 -> -13.603952 | AL1001: =IF(S1001=0,"",AJ1001/S1001) -> 9.2658561 | AM1001: =IF(S1001=0,"",AI1001/S1001) -> 12.736535 | AN1001: =IF(T1001=0,"",U1001/T1001) -> 0.99663247 | AO1001: =IF(H1001=0,"",T1001/H1001) -> 2.1382886 | AP1001: =IF(H1001=0,"",U1001/H1001) -> 2.1310879 | AQ1001: =IF(Z1001=0,"",AC1001/Z1001) -> 0.48439349 | AR1001: =IF(H1001=0,"",J1001/H1001) -> 0.93301318 | AS1001: =IF(E1001=0,"",V1001/E1001) -> 5.1665085

Sheet Umbrales
A1: Sector | B1: percentil 75 ebitda_margin | C1: percentil 75 cfo_margin | D1: percentil 90 capex_intensity | E1: percentil 75 assets_to_revenue_x | F1: percentil 50 fcf_reported_mm/revenue_reported_mm | G1: percentil 25 maint_capex_share | H1: percentil 75 dcf_fcf_gap_mm / revenue_reported_mm | I1: percentil 75 npl_growth_pct | J1: percentil 25 credit_loss_coverage_reported_x | K1: percentil 10 debt_end_to_avg_x
A2: Consumer | B2: {=_xlfn.PERCENTILE.INC(IF(Datos!$C$2:$C$1001=A2,Datos!$AE$2:$AE$1001),0.75)} -> 0.18290796 | C2: {=_xlfn.PERCENTILE.INC(IF(Datos!$C$2:$C$1001=A2,Datos!$AF$2:$AF$1001),0.75)} -> 0.12205009 | D2: {=_xlfn.PERCENTILE.INC(IF(Datos!$C$2:$C$1001=A2,Datos!$AG$2:$AG$1001),0.9)} -> 0.077863509 | E2: {=_xlfn.PERCENTILE.INC(IF(Datos!$C$2:$C$1001=A2,Datos!$AS$2:$AS$1001),0.75)} -> 1.5232589 | F2: {=_xlfn.PERCENTILE.INC(IF(Datos!$C$2:$C$1001=A2,Datos!$AI$2:$AI$1001/Datos!$E$2:$E$1001),0.5)} -> 0.031674636 | G2: {=_xlfn.PERCENTILE.INC(IF(Datos!$C$2:$C$1001=A2,Datos!$AH$2:$AH$1001),0.25)} -> 0.50851978 | H2: {=_xlfn.PERCENTILE.INC(IF(Datos!$C$2:$C$1001=A2,Datos!$AK$2:$AK$1001/Datos!$E$2:$E$1001),0.75)} -> 0.060665521 | K2: {=_xlfn.PERCENTILE.INC(IF(Datos!$C$2:$C$1001=A2,Datos!$AN$2:$AN$1001),0.1)} -> 0.94977598
A3: Energy | B3: {=_xlfn.PERCENTILE.INC(IF(Datos!$C$2:$C$1001=A3,Datos!$AE$2:$AE$1001),0.75)} -> 0.31196393 | C3: {=_xlfn.PERCENTILE.INC(IF(Datos!$C$2:$C$1001=A3,Datos!$AF$2:$AF$1001),0.75)} -> 0.22086835 | D3: {=_xlfn.PERCENTILE.INC(IF(Datos!$C$2:$C$1001=A3,Datos!$AG$2:$AG$1001),0.9)} -> 0.28991455 | E3: {=_xlfn.PERCENTILE.INC(IF(Datos!$C$2:$C$1001=A3,Datos!$AS$2:$AS$1001),0.75)} -> 2.8980395 | F3: {=_xlfn.PERCENTILE.INC(IF(Datos!$C$2:$C$1001=A3,Datos!$AI$2:$AI$1001/Datos!$E$2:$E$1001),0.5)} -> -0.051192663 | G3: {=_xlfn.PERCENTILE.INC(IF(Datos!$C$2:$C$1001=A3,Datos!$AH$2:$AH$1001),0.25)} -> 0.58288412 | H3: {=_xlfn.PERCENTILE.INC(IF(Datos!$C$2:$C$1001=A3,Datos!$AK$2:$AK$1001/Datos!$E$2:$E$1001),0.75)} -> 0.12091227 | K3: {=_xlfn.PERCENTILE.INC(IF(Datos!$C$2:$C$1001=A3,Datos!$AN$2:$AN$1001),0.1)} -> 0.95246281
A4: Financials | B4: {=_xlfn.PERCENTILE.INC(IF(Datos!$C$2:$C$1001=A4,Datos!$AE$2:$AE$1001),0.75)} -> 0.38877435 | C4: {=_xlfn.PERCENTILE.INC(IF(Datos!$C$2:$C$1001=A4,Datos!$AF$2:$AF$1001),0.75)} -> 0.28427196 | D4: {=_xlfn.PERCENTILE.INC(IF(Datos!$C$2:$C$1001=A4,Datos!$AG$2:$AG$1001),0.9)} -> 0.037547325 | E4: {=_xlfn.PERCENTILE.INC(IF(Datos!$C$2:$C$1001=A4,Datos!$AS$2:$AS$1001),0.75)} -> 5.6564154 | F4: {=_xlfn.PERCENTILE.INC(IF(Datos!$C$2:$C$1001=A4,Datos!$AI$2:$AI$1001/Datos!$E$2:$E$1001),0.5)} -> 0.21790144 | G4: {=_xlfn.PERCENTILE.INC(IF(Datos!$C$2:$C$1001=A4,Datos!$AH$2:$AH$1001),0.25)} -> 0.45222619 | H4: {=_xlfn.PERCENTILE.INC(IF(Datos!$C$2:$C$1001=A4,Datos!$AK$2:$AK$1001/Datos!$E$2:$E$1001),0.75)} -> 0.018748568 | I4: {=_xlfn.PERCENTILE.INC(IF(Datos!$C$2:$C$1001=A4,Datos!$AA$2:$AA$1001),0.75)} -> 0.20554363 | J4: {=_xlfn.PERCENTILE.INC(IF(Datos!$C$2:$C$1001=A4,Datos!$AQ$2:$AQ$1001),0.25)} -> 0.33577849 | K4: {=_xlfn.PERCENTILE.INC(IF(Datos!$C$2:$C$1001=A4,Datos!$AN$2:$AN$1001),0.1)} -> 0.94867619
A5: Industrials | B5: {=_xlfn.PERCENTILE.INC(IF(Datos!$C$2:$C$1001=A5,Datos!$AE$2:$AE$1001),0.75)} -> 0.20187193 | C5: {=_xlfn.PERCENTILE.INC(IF(Datos!$C$2:$C$1001=A5,Datos!$AF$2:$AF$1001),0.75)} -> 0.13780716 | D5: {=_xlfn.PERCENTILE.INC(IF(Datos!$C$2:$C$1001=A5,Datos!$AG$2:$AG$1001),0.9)} -> 0.14324173 | E5: {=_xlfn.PERCENTILE.INC(IF(Datos!$C$2:$C$1001=A5,Datos!$AS$2:$AS$1001),0.75)} -> 2.1323077 | F5: {=_xlfn.PERCENTILE.INC(IF(Datos!$C$2:$C$1001=A5,Datos!$AI$2:$AI$1001/Datos!$E$2:$E$1001),0.5)} -> -0.0035903294 | G5: {=_xlfn.PERCENTILE.INC(IF(Datos!$C$2:$C$1001=A5,Datos!$AH$2:$AH$1001),0.25)} -> 0.50521966 | H5: {=_xlfn.PERCENTILE.INC(IF(Datos!$C$2:$C$1001=A5,Datos!$AK$2:$AK$1001/Datos!$E$2:$E$1001),0.75)} -> 0.077995567 | K5: {=_xlfn.PERCENTILE.INC(IF(Datos!$C$2:$C$1001=A5,Datos!$AN$2:$AN$1001),0.1)} -> 0.94976269
A6: Technology | B6: {=_xlfn.PERCENTILE.INC(IF(Datos!$C$2:$C$1001=A6,Datos!$AE$2:$AE$1001),0.75)} -> 0.29147892 | C6: {=_xlfn.PERCENTILE.INC(IF(Datos!$C$2:$C$1001=A6,Datos!$AF$2:$AF$1001),0.75)} -> 0.20310035 | D6: {=_xlfn.PERCENTILE.INC(IF(Datos!$C$2:$C$1001=A6,Datos!$AG$2:$AG$1001),0.9)} -> 0.085944599 | E6: {=_xlfn.PERCENTILE.INC(IF(Datos!$C$2:$C$1001=A6,Datos!$AS$2:$AS$1001),0.75)} -> 1.6026025 | F6: {=_xlfn.PERCENTILE.INC(IF(Datos!$C$2:$C$1001=A6,Datos!$AI$2:$AI$1001/Datos!$E$2:$E$1001),0.5)} -> 0.11012364 | G6: {=_xlfn.PERCENTILE.INC(IF(Datos!$C$2:$C$1001=A6,Datos!$AH$2:$AH$1001),0.25)} -> 0.41762511 | H6: {=_xlfn.PERCENTILE.INC(IF(Datos!$C$2:$C$1001=A6,Datos!$AK$2:$AK$1001/Datos!$E$2:$E$1001),0.75)} -> 0.054196816 | K6: {=_xlfn.PERCENTILE.INC(IF(Datos!$C$2:$C$1001=A6,Datos!$AN$2:$AN$1001),0.1)} -> 0.94630804

Sheet Flags
A1: firm_id | B1: sector | C1: fcf_margin (AI/E) | D1: percentil 75 ebitda_margin | E1: =Umbrales!C1 -> percentil 75 cfo_margin | F1: percentil 90 capex_intensity | G1: percentil 75 assets_to_revenue_x | H1: percentil 50 fcf_reported_mm/revenue_reported_mm | I1: Flag 1 capitalización gastos | J1: dcf_fcf_gap_mm / revenue_reported_mm | K1: =Umbrales!G1 -> percentil 25 maint_capex_share | L1: percentil 75 dcf_fcf_gap_mm / revenue_reported_mm | M1: Flag 2 Tipo Linn | N1: percentil 75 npl_growth_pct | O1: percentil 25 credit_loss_coverage_reported_x | P1: Flag 3 Tipo New Century | Q1: percentil 10 debt_end_to_avg_x | R1: Flag 4 Tipo Lehman | S1: Weight | T1: Red flag score | U1: Cantidad de flags activadas | V1: Flags detectadas
A2: =ParticipantesCrossSectionTable[[#This Row],[firm_id]] -> F0902 | B2: =ParticipantesCrossSectionTable[[#This Row],[sector]] -> Consumer | C2: =ParticipantesCrossSectionTable[[#This Row],[fcf_reported_mm]]/ParticipantesCrossSectionTable[[#This Row],[revenue_reported_mm]] -> 0.094675636 | D2: =VLOOKUP(B2,Umbrales!$A$2:$F$6,2,FALSE) -> 0.18290796 | E2: =VLOOKUP(B2,Umbrales!$A$2:$F$6,3,FALSE) -> 0.12205009 | F2: =VLOOKUP(B2,Umbrales!$A$2:$F$6,4,FALSE) -> 0.077863509 | G2: =VLOOKUP(B2,Umbrales!$A$2:$F$6,5,FALSE) -> 1.5232589 | H2: =VLOOKUP(B2,Umbrales!$A$2:$F$6,6,FALSE) -> 0.031674636 | I2: =IF(AND(Datos!AE2>D2,Datos!AF2>E2,Datos!AG2>F2,Datos!AS2>G2,C2<H2),1,0) -> 0 | J2: =ParticipantesCrossSectionTable[[#This Row],[dcf_fcf_gap_mm]]/ParticipantesCrossSectionTable[[#This Row],[revenue_reported_mm]] -> 0.021064762 | K2: =VLOOKUP(B2,Umbrales!$A$2:$H$6,7,FALSE) -> 0.50851978 | L2: =VLOOKUP(B2,Umbrales!$A$2:$H$6,8,FALSE) -> 0.060665521 | M2: =IF(AND(Datos!S2>0,Datos!AH2<K2,Datos!AL2>=1,Datos!AM2<1,J2>L2),1,0) -> 0 | N2: =VLOOKUP(B2,Umbrales!$A$2:$J$6,9,FALSE) -> 0 | O2: =VLOOKUP(B2,Umbrales!$A$2:$J$6,10,FALSE) -> 0 | P2: =IF(AND(Datos!C2="Financials",Datos!AA2>N2,Datos!AD2<0,Datos!AQ2<O2),1,0) -> 0 | Q2: =VLOOKUP(B2,Umbrales!$A$2:$K$6,11,FALSE) -> 0.94977598 | R2: =IF(AND(Datos!AN2<0.85,Datos!AN2<Q2),1,0) -> 0 | S2: =1+IF(Datos!S2>0,1,0)+IF(Datos!C2="Financials",1.2,0)+1.3 -> 3.3 | T2: =(I2*1+M2*IF(Datos!S2>0,1,0)+P2*IF(Datos!C2="Financials",1,0)+R2*1.3)/S2 -> 0 | U2: =I2+M2+P2+R2 -> 0 | V2: =IF(I2=1,"Flag1 ","")&IF(M2=1,"Flag2 ","")&IF(P2=1,"Flag3 ","")&IF(R2=1,"Flag4 ","")
A3: =ParticipantesCrossSectionTable[[#This Row],[firm_id]] -> F0433 | B3: =ParticipantesCrossSectionTable[[#This Row],[sector]] -> Technology | C3: =ParticipantesCrossSectionTable[[#This Row],[fcf_reported_mm]]/ParticipantesCrossSectionTable[[#This Row],[revenue_reported_mm]] -> 0.12246621 | D3: =VLOOKUP(B3,Umbrales!$A$2:$F$6,2,FALSE) -> 0.29147892 | E3: =VLOOKUP(B3,Umbrales!$A$2:$F$6,3,FALSE) -> 0.20310035 | F3: =VLOOKUP(B3,Umbrales!$A$2:$F$6,4,FALSE) -> 0.085944599 | G3: =VLOOKUP(B3,Umbrales!$A$2:$F$6,5,FALSE) -> 1.6026025 | H3: =VLOOKUP(B3,Umbrales!$A$2:$F$6,6,FALSE) -> 0.11012364 | I3: =IF(AND(Datos!AE3>D3,Datos!AF3>E3,Datos!AG3>F3,Datos!AS3>G3,C3<H3),1,0) -> 0 | J3: =ParticipantesCrossSectionTable[[#This Row],[dcf_fcf_gap_mm]]/ParticipantesCrossSectionTable[[#This Row],[revenue_reported_mm]] -> 0.077214941 | K3: =VLOOKUP(B3,Umbrales!$A$2:$H$6,7,FALSE) -> 0.41762511 | L3: =VLOOKUP(B3,Umbrales!$A$2:$H$6,8,FALSE) -> 0.054196816 | M3: =IF(AND(Datos!S3>0,Datos!AH3<K3,Datos!AL3>=1,Datos!AM3<1,J3>L3),1,0) -> 0 | N3: =VLOOKUP(B3,Umbrales!$A$2:$J$6,9,FALSE) -> 0 | O3: =VLOOKUP(B3,Umbrales!$A$2:$J$6,10,FALSE) -> 0 | P3: =IF(AND(Datos!C3="Financials",Datos!AA3>N3,Datos!AD3<0,Datos!AQ3<O3),1,0) -> 0 | Q3: =VLOOKUP(B3,Umbrales!$A$2:$K$6,11,FALSE) -> 0.94630804 | R3: =IF(AND(Datos!AN3<0.85,Datos!AN3<Q3),1,0) -> 0 | S3: =1+IF(Datos!S3>0,1,0)+IF(Datos!C3="Financials",1.2,0)+1.3 -> 3.3 | T3: =(I3*1+M3*IF(Datos!S3>0,1,0)+P3*IF(Datos!C3="Financials",1,0)+R3*1.3)/S3 -> 0 | U3: =I3+M3+P3+R3 -> 0 | V3: =IF(I3=1,"Flag1 ","")&IF(M3=1,"Flag2 ","")&IF(P3=1,"Flag3 ","")&IF(R3=1,"Flag4 ","")
A4: =ParticipantesCrossSectionTable[[#This Row],[firm_id]] -> F0060 | B4: =ParticipantesCrossSectionTable[[#This Row],[sector]] -> Energy | C4: =ParticipantesCrossSectionTable[[#This Row],[fcf_reported_mm]]/ParticipantesCrossSectionTable[[#This Row],[revenue_reported_mm]] -> -0.0024173841 | D4: =VLOOKUP(B4,Umbrales!$A$2:$F$6,2,FALSE) -> 0.31196393 | E4: =VLOOKUP(B4,Umbrales!$A$2:$F$6,3,FALSE) -> 0.22086835 | F4: =VLOOKUP(B4,Umbrales!$A$2:$F$6,4,FALSE) -> 0.28991455 | G4: =VLOOKUP(B4,Umbrales!$A$2:$F$6,5,FALSE) -> 2.8980395 | H4: =VLOOKUP(B4,Umbrales!$A$2:$F$6,6,FALSE) -> -0.051192663 | I4: =IF(AND(Datos!AE4>D4,Datos!AF4>E4,Datos!AG4>F4,Datos!AS4>G4,C4<H4),1,0) -> 0 | J4: =ParticipantesCrossSectionTable[[#This Row],[dcf_fcf_gap_mm]]/ParticipantesCrossSectionTable[[#This Row],[revenue_reported_mm]] -> 0.060429955 | K4: =VLOOKUP(B4,Umbrales!$A$2:$H$6,7,FALSE) -> 0.58288412 | L4: =VLOOKUP(B4,Umbrales!$A$2:$H$6,8,FALSE) -> 0.12091227 | M4: =IF(AND(Datos!S4>0,Datos!AH4<K4,Datos!AL4>=1,Datos!AM4<1,J4>L4),1,0) -> 0 | N4: =VLOOKUP(B4,Umbrales!$A$2:$J$6,9,FALSE) -> 0 | O4: =VLOOKUP(B4,Umbrales!$A$2:$J$6,10,FALSE) -> 0 | P4: =IF(AND(Datos!C4="Financials",Datos!AA4>N4,Datos!AD4<0,Datos!AQ4<O4),1,0) -> 0 | Q4: =VLOOKUP(B4,Umbrales!$A$2:$K$6,11,FALSE) -> 0.95246281 | R4: =IF(AND(Datos!AN4<0.85,Datos!AN4<Q4),1,0) -> 0 | S4: =1+IF(Datos!S4>0,1,0)+IF(Datos!C4="Financials",1.2,0)+1.3 -> 3.3 | T4: =(I4*1+M4*IF(Datos!S4>0,1,0)+P4*IF(Datos!C4="Financials",1,0)+R4*1.3)/S4 -> 0 | U4: =I4+M4+P4+R4 -> 0 | V4: =IF(I4=1,"Flag1 ","")&IF(M4=1,"Flag2 ","")&IF(P4=1,"Flag3 ","")&IF(R4=1,"Flag4 ","")
A5: =ParticipantesCrossSectionTable[[#This Row],[firm_id]] -> F0257 | B5: =ParticipantesCrossSectionTable[[#This Row],[sector]] -> Financials | C5: =ParticipantesCrossSectionTable[[#This Row],[fcf_reported_mm]]/ParticipantesCrossSectionTable[[#This Row],[revenue_reported_mm]] -> 0.155931 | D5: =VLOOKUP(B5,Umbrales!$A$2:$F$6,2,FALSE) -> 0.38877435 | E5: =VLOOKUP(B5,Umbrales!$A$2:$F$6,3,FALSE) -> 0.28427196 | F5: =VLOOKUP(B5,Umbrales!$A$2:$F$6,4,FALSE) -> 0.037547325 | G5: =VLOOKUP(B5,Umbrales!$A$2:$F$6,5,FALSE) -> 5.6564154 | H5: =VLOOKUP(B5,Umbrales!$A$2:$F$6,6,FALSE) -> 0.21790144 | I5: =IF(AND(Datos!AE5>D5,Datos!AF5>E5,Datos!AG5>F5,Datos!AS5>G5,C5<H5),1,0) -> 0 | J5: =ParticipantesCrossSectionTable[[#This Row],[dcf_fcf_gap_mm]]/ParticipantesCrossSectionTable[[#This Row],[revenue_reported_mm]] -> 0.057049236 | K5: =VLOOKUP(B5,Umbrales!$A$2:$H$6,7,FALSE) -> 0.45222619 | L5: =VLOOKUP(B5,Umbrales!$A$2:$H$6,8,FALSE) -> 0.018748568 | M5: =IF(AND(Datos!S5>0,Datos!AH5<K5,Datos!AL5>=1,Datos!AM5<1,J5>L5),1,0) -> 0 | N5: =VLOOKUP(B5,Umbrales!$A$2:$J$6,9,FALSE) -> 0.20554363 | O5: =VLOOKUP(B5,Umbrales!$A$2:$J$6,10,FALSE) -> 0.33577849 | P5: =IF(AND(Datos!C5="Financials",Datos!AA5>N5,Datos!AD5<0,Datos!AQ5<O5),1,0) -> 0 | Q5: =VLOOKUP(B5,Umbrales!$A$2:$K$6,11,FALSE) -> 0.94867619 | R5: =IF(AND(Datos!AN5<0.85,Datos!AN5<Q5),1,0) -> 0 | S5: =1+IF(Datos!S5>0,1,0)+IF(Datos!C5="Financials",1.2,0)+1.3 -> 4.5 | T5: =(I5*1+M5*IF(Datos!S5>0,1,0)+P5*IF(Datos!C5="Financials",1,0)+R5*1.3)/S5 -> 0 | U5: =I5+M5+P5+R5 -> 0 | V5: =IF(I5=1,"Flag1 ","")&IF(M5=1,"Flag2 ","")&IF(P5=1,"Flag3 ","")&IF(R5=1,"Flag4 ","")
A6: =ParticipantesCrossSectionTable[[#This Row],[firm_id]] -> F0057 | B6: =ParticipantesCrossSectionTable[[#This Row],[sector]] -> Energy | C6: =ParticipantesCrossSectionTable[[#This Row],[fcf_reported_mm]]/ParticipantesCrossSectionTable[[#This Row],[revenue_reported_mm]] -> 0.013002452 | D6: =VLOOKUP(B6,Umbrales!$A$2:$F$6,2,FALSE) -> 0.31196393 | E6: =VLOOKUP(B6,Umbrales!$A$2:$F$6,3,FALSE) -> 0.22086835 | F6: =VLOOKUP(B6,Umbrales!$A$2:$F$6,4,FALSE) -> 0.28991455 | G6: =VLOOKUP(B6,Umbrales!$A$2:$F$6,5,FALSE) -> 2.8980395 | H6: =VLOOKUP(B6,Umbrales!$A$2:$F$6,6,FALSE) -> -0.051192663 | I6: =IF(AND(Datos!AE6>D6,Datos!AF6>E6,Datos!AG6>F6,Datos!AS6>G6,C6<H6),1,0) -> 0 | J6: =ParticipantesCrossSectionTable[[#This Row],[dcf_fcf_gap_mm]]/ParticipantesCrossSectionTable[[#This Row],[revenue_reported_mm]] -> 0.049680118 | K6: =VLOOKUP(B6,Umbrales!$A$2:$H$6,7,FALSE) -> 0.58288412 | L6: =VLOOKUP(B6,Umbrales!$A$2:$H$6,8,FALSE) -> 0.12091227 | M6: =IF(AND(Datos!S6>0,Datos!AH6<K6,Datos!AL6>=1,Datos!AM6<1,J6>L6),1,0) -> 0 | N6: =VLOOKUP(B6,Umbrales!$A$2:$J$6,9,FALSE) -> 0 | O6: =VLOOKUP(B6,Umbrales!$A$2:$J$6,10,FALSE) -> 0 | P6: =IF(AND(Datos!C6="Financials",Datos!AA6>N6,Datos!AD6<0,Datos!AQ6<O6),1,0) -> 0 | Q6: =VLOOKUP(B6,Umbrales!$A$2:$K$6,11,FALSE) -> 0.95246281 | R6: =IF(AND(Datos!AN6<0.85,Datos!AN6<Q6),1,0) -> 0 | S6: =1+IF(Datos!S6>0,1,0)+IF(Datos!C6="Financials",1.2,0)+1.3 -> 3.3 | T6: =(I6*1+M6*IF(Datos!S6>0,1,0)+P6*IF(Datos!C6="Financials",1,0)+R6*1.3)/S6 -> 0 | U6: =I6+M6+P6+R6 -> 0 | V6: =IF(I6=1,"Flag1 ","")&IF(M6=1,"Flag2 ","")&IF(P6=1,"Flag3 ","")&IF(R6=1,"Flag4 ","")
A7: =ParticipantesCrossSectionTable[[#This Row],[firm_id]] -> F0657 | B7: =ParticipantesCrossSectionTable[[#This Row],[sector]] -> Industrials | C7: =ParticipantesCrossSectionTable[[#This Row],[fcf_reported_mm]]/ParticipantesCrossSectionTable[[#This Row],[revenue_reported_mm]] -> 0.0059857745 | D7: =VLOOKUP(B7,Umbrales!$A$2:$F$6,2,FALSE) -> 0.20187193 | E7: =VLOOKUP(B7,Umbrales!$A$2:$F$6,3,FALSE) -> 0.13780716 | F7: =VLOOKUP(B7,Umbrales!$A$2:$F$6,4,FALSE) -> 0.14324173 | G7: =VLOOKUP(B7,Umbrales!$A$2:$F$6,5,FALSE) -> 2.1323077 | H7: =VLOOKUP(B7,Umbrales!$A$2:$F$6,6,FALSE) -> -0.0035903294 | I7: =IF(AND(Datos!AE7>D7,Datos!AF7>E7,Datos!AG7>F7,Datos!AS7>G7,C7<H7),1,0) -> 0 | J7: =ParticipantesCrossSectionTable[[#This Row],[dcf_fcf_gap_mm]]/ParticipantesCrossSectionTable[[#This Row],[revenue_reported_mm]] -> 0.024638073 | K7: =VLOOKUP(B7,Umbrales!$A$2:$H$6,7,FALSE) -> 0.50521966 | L7: =VLOOKUP(B7,Umbrales!$A$2:$H$6,8,FALSE) -> 0.077995567 | M7: =IF(AND(Datos!S7>0,Datos!AH7<K7,Datos!AL7>=1,Datos!AM7<1,J7>L7),1,0) -> 0 | N7: =VLOOKUP(B7,Umbrales!$A$2:$J$6,9,FALSE) -> 0 | O7: =VLOOKUP(B7,Umbrales!$A$2:$J$6,10,FALSE) -> 0 | P7: =IF(AND(Datos!C7="Financials",Datos!AA7>N7,Datos!AD7<0,Datos!AQ7<O7),1,0) -> 0 | Q7: =VLOOKUP(B7,Umbrales!$A$2:$K$6,11,FALSE) -> 0.94976269 | R7: =IF(AND(Datos!AN7<0.85,Datos!AN7<Q7),1,0) -> 0 | S7: =1+IF(Datos!S7>0,1,0)+IF(Datos!C7="Financials",1.2,0)+1.3 -> 3.3 | T7: =(I7*1+M7*IF(Datos!S7>0,1,0)+P7*IF(Datos!C7="Financials",1,0)+R7*1.3)/S7 -> 0 | U7: =I7+M7+P7+R7 -> 0 | V7: =IF(I7=1,"Flag1 ","")&IF(M7=1,"Flag2 ","")&IF(P7=1,"Flag3 ","")&IF(R7=1,"Flag4 ","")
A8: =ParticipantesCrossSectionTable[[#This Row],[firm_id]] -> F0773 | B8: =ParticipantesCrossSectionTable[[#This Row],[sector]] -> Industrials | C8: =ParticipantesCrossSectionTable[[#This Row],[fcf_reported_mm]]/ParticipantesCrossSectionTable[[#This Row],[revenue_reported_mm]] -> 0.12293248 | D8: =VLOOKUP(B8,Umbrales!$A$2:$F$6,2,FALSE) -> 0.20187193 | E8: =VLOOKUP(B8,Umbrales!$A$2:$F$6,3,FALSE) -> 0.13780716 | F8: =VLOOKUP(B8,Umbrales!$A$2:$F$6,4,FALSE) -> 0.14324173 | G8: =VLOOKUP(B8,Umbrales!$A$2:$F$6,5,FALSE) -> 2.1323077 | H8: =VLOOKUP(B8,Umbrales!$A$2:$F$6,6,FALSE) -> -0.0035903294 | I8: =IF(AND(Datos!AE8>D8,Datos!AF8>E8,Datos!AG8>F8,Datos!AS8>G8,C8<H8),1,0) -> 0 | J8: =ParticipantesCrossSectionTable[[#This Row],[dcf_fcf_gap_mm]]/ParticipantesCrossSectionTable[[#This Row],[revenue_reported_mm]] -> 0.021090542 | K8: =VLOOKUP(B8,Umbrales!$A$2:$H$6,7,FALSE) -> 0.50521966 | L8: =VLOOKUP(B8,Umbrales!$A$2:$H$6,8,FALSE) -> 0.077995567 | M8: =IF(AND(Datos!S8>0,Datos!AH8<K8,Datos!AL8>=1,Datos!AM8<1,J8>L8),1,0) -> 0 | N8: =VLOOKUP(B8,Umbrales!$A$2:$J$6,9,FALSE) -> 0 | O8: =VLOOKUP(B8,Umbrales!$A$2:$J$6,10,FALSE) -> 0 | P8: =IF(AND(Datos!C8="Financials",Datos!AA8>N8,Datos!AD8<0,Datos!AQ8<O8),1,0) -> 0 | Q8: =VLOOKUP(B8,Umbrales!$A$2:$K$6,11,FALSE) -> 0.94976269 | R8: =IF(AND(Datos!AN8<0.85,Datos!AN8<Q8),1,0) -> 0 | S8: =1+IF(Datos!S8>0,1,0)+IF(Datos!C8="Financials",1.2,0)+1.3 -> 3.3 | T8: =(I8*1+M8*IF(Datos!S8>0,1,0)+P8*IF(Datos!C8="Financials",1,0)+R8*1.3)/S8 -> 0 | U8: =I8+M8+P8+R8 -> 0 | V8: =IF(I8=1,"Flag1 ","")&IF(M8=1,"Flag2 ","")&IF(P8=1,"Flag3 ","")&IF(R8=1,"Flag4 ","")
A9: =ParticipantesCrossSectionTable[[#This Row],[firm_id]] -> F0574 | B9: =ParticipantesCrossSectionTable[[#This Row],[sector]] -> Technology | C9: =ParticipantesCrossSectionTable[[#This Row],[fcf_reported_mm]]/ParticipantesCrossSectionTable[[#This Row],[revenue_reported_mm]] -> 0.044205475 | D9: =VLOOKUP(B9,Umbrales!$A$2:$F$6,2,FALSE) -> 0.29147892 | E9: =VLOOKUP(B9,Umbrales!$A$2:$F$6,3,FALSE) -> 0.20310035 | F9: =VLOOKUP(B9,Umbrales!$A$2:$F$6,4,FALSE) -> 0.085944599 | G9: =VLOOKUP(B9,Umbrales!$A$2:$F$6,5,FALSE) -> 1.6026025 | H9: =VLOOKUP(B9,Umbrales!$A$2:$F$6,6,FALSE) -> 0.11012364 | I9: =IF(AND(Datos!AE9>D9,Datos!AF9>E9,Datos!AG9>F9,Datos!AS9>G9,C9<H9),1,0) -> 0 | J9: =ParticipantesCrossSectionTable[[#This Row],[dcf_fcf_gap_mm]]/ParticipantesCrossSectionTable[[#This Row],[revenue_reported_mm]] -> 0.07443085 | K9: =VLOOKUP(B9,Umbrales!$A$2:$H$6,7,FALSE) -> 0.41762511 | L9: =VLOOKUP(B9,Umbrales!$A$2:$H$6,8,FALSE) -> 0.054196816 | M9: =IF(AND(Datos!S9>0,Datos!AH9<K9,Datos!AL9>=1,Datos!AM9<1,J9>L9),1,0) -> 0 | N9: =VLOOKUP(B9,Umbrales!$A$2:$J$6,9,FALSE) -> 0 | O9: =VLOOKUP(B9,Umbrales!$A$2:$J$6,10,FALSE) -> 0 | P9: =IF(AND(Datos!C9="Financials",Datos!AA9>N9,Datos!AD9<0,Datos!AQ9<O9),1,0) -> 0 | Q9: =VLOOKUP(B9,Umbrales!$A$2:$K$6,11,FALSE) -> 0.94630804 | R9: =IF(AND(Datos!AN9<0.85,Datos!AN9<Q9),1,0) -> 0 | S9: =1+IF(Datos!S9>0,1,0)+IF(Datos!C9="Financials",1.2,0)+1.3 -> 3.3 | T9: =(I9*1+M9*IF(Datos!S9>0,1,0)+P9*IF(Datos!C9="Financials",1,0)+R9*1.3)/S9 -> 0 | U9: =I9+M9+P9+R9 -> 0 | V9: =IF(I9=1,"Flag1 ","")&IF(M9=1,"Flag2 ","")&IF(P9=1,"Flag3 ","")&IF(R9=1,"Flag4 ","")
A10: =ParticipantesCrossSectionTable[[#This Row],[firm_id]] -> F0438 | B10: =ParticipantesCrossSectionTable[[#This Row],[sector]] -> Technology | C10: =ParticipantesCrossSectionTable[[#This Row],[fcf_reported_mm]]/ParticipantesCrossSectionTable[[#This Row],[revenue_reported_mm]] -> 0.091195038 | D10: =VLOOKUP(B10,Umbrales!$A$2:$F$6,2,FALSE) -> 0.29147892 | E10: =VLOOKUP(B10,Umbrales!$A$2:$F$6,3,FALSE) -> 0.20310035 | F10: =VLOOKUP(B10,Umbrales!$A$2:$F$6,4,FALSE) -> 0.085944599 | G10: =VLOOKUP(B10,Umbrales!$A$2:$F$6,5,FALSE) -> 1.6026025 | H10: =VLOOKUP(B10,Umbrales!$A$2:$F$6,6,FALSE) -> 0.11012364 | I10: =IF(AND(Datos!AE10>D10,Datos!AF10>E10,Datos!AG10>F10,Datos!AS10>G10,C10<H10),1,0) -> 0 | J10: =ParticipantesCrossSectionTable[[#This Row],[dcf_fcf_gap_mm]]/ParticipantesCrossSectionTable[[#This Row],[revenue_reported_mm]] -> 0.039467969 | K10: =VLOOKUP(B10,Umbrales!$A$2:$H$6,7,FALSE) -> 0.41762511 | L10: =VLOOKUP(B10,Umbrales!$A$2:$H$6,8,FALSE) -> 0.054196816 | M10: =IF(AND(Datos!S10>0,Datos!AH10<K10,Datos!AL10>=1,Datos!AM10<1,J10>L10),1,0) -> 0 | N10: =VLOOKUP(B10,Umbrales!$A$2:$J$6,9,FALSE) -> 0 | O10: =VLOOKUP(B10,Umbrales!$A$2:$J$6,10,FALSE) -> 0 | P10: =IF(AND(Datos!C10="Financials",Datos!AA10>N10,Datos!AD10<0,Datos!AQ10<O10),1,0) -> 0 | Q10: =VLOOKUP(B10,Umbrales!$A$2:$K$6,11,FALSE) -> 0.94630804 | R10: =IF(AND(Datos!AN10<0.85,Datos!AN10<Q10),1,0) -> 0 | S10: =1+IF(Datos!S10>0,1,0)+IF(Datos!C10="Financials",1.2,0)+1.3 -> 3.3 | T10: =(I10*1+M10*IF(Datos!S10>0,1,0)+P10*IF(Datos!C10="Financials",1,0)+R10*1.3)/S10 -> 0 | U10: =I10+M10+P10+R10 -> 0 | V10: =IF(I10=1,"Flag1 ","")&IF(M10=1,"Flag2 ","")&IF(P10=1,"Flag3 ","")&IF(R10=1,"Flag4 ","")
A11: =ParticipantesCrossSectionTable[[#This Row],[firm_id]] -> F0375 | B11: =ParticipantesCrossSectionTable[[#This Row],[sector]] -> Financials | C11: =ParticipantesCrossSectionTable[[#This Row],[fcf_reported_mm]]/ParticipantesCrossSectionTable[[#This Row],[revenue_reported_mm]] -> 0.20711459 | D11: =VLOOKUP(B11,Umbrales!$A$2:$F$6,2,FALSE) -> 0.38877435 | E11: =VLOOKUP(B11,Umbrales!$A$2:$F$6,3,FALSE) -> 0.28427196 | F11: =VLOOKUP(B11,Umbrales!$A$2:$F$6,4,FALSE) -> 0.037547325 | G11: =VLOOKUP(B11,Umbrales!$A$2:$F$6,5,FALSE) -> 5.6564154 | H11: =VLOOKUP(B11,Umbrales!$A$2:$F$6,6,FALSE) -> 0.21790144 | I11: =IF(AND(Datos!AE11>D11,Datos!AF11>E11,Datos!AG11>F11,Datos!AS11>G11,C11<H11),1,0) -> 0 | J11: =ParticipantesCrossSectionTable[[#This Row],[dcf_fcf_gap_mm]]/ParticipantesCrossSectionTable[[#This Row],[revenue_reported_mm]] -> -0.0067471496 | K11: =VLOOKUP(B11,Umbrales!$A$2:$H$6,7,FALSE) -> 0.45222619 | L11: =VLOOKUP(B11,Umbrales!$A$2:$H$6,8,FALSE) -> 0.018748568 | M11: =IF(AND(Datos!S11>0,Datos!AH11<K11,Datos!AL11>=1,Datos!AM11<1,J11>L11),1,0) -> 0 | N11: =VLOOKUP(B11,Umbrales!$A$2:$J$6,9,FALSE) -> 0.20554363 | O11: =VLOOKUP(B11,Umbrales!$A$2:$J$6,10,FALSE) -> 0.33577849 | P11: =IF(AND(Datos!C11="Financials",Datos!AA11>N11,Datos!AD11<0,Datos!AQ11<O11),1,0) -> 0 | Q11: =VLOOKUP(B11,Umbrales!$A$2:$K$6,11,FALSE) -> 0.94867619 | R11: =IF(AND(Datos!AN11<0.85,Datos!AN11<Q11),1,0) -> 0 | S11: =1+IF(Datos!S11>0,1,0)+IF(Datos!C11="Financials",1.2,0)+1.3 -> 4.5 | T11: =(I11*1+M11*IF(Datos!S11>0,1,0)+P11*IF(Datos!C11="Financials",1,0)+R11*1.3)/S11 -> 0 | U11: =I11+M11+P11+R11 -> 0 | V11: =IF(I11=1,"Flag1 ","")&IF(M11=1,"Flag2 ","")&IF(P11=1,"Flag3 ","")&IF(R11=1,"Flag4 ","")
A12: =ParticipantesCrossSectionTable[[#This Row],[firm_id]] -> F0296 | B12: =ParticipantesCrossSectionTable[[#This Row],[sector]] -> Financials | C12: =ParticipantesCrossSectionTable[[#This Row],[fcf_reported_mm]]/ParticipantesCrossSectionTable[[#This Row],[revenue_reported_mm]] -> 0.28279999 | D12: =VLOOKUP(B12,Umbrales!$A$2:$F$6,2,FALSE) -> 0.38877435 | E12: =VLOOKUP(B12,Umbrales!$A$2:$F$6,3,FALSE) -> 0.28427196 | F12: =VLOOKUP(B12,Umbrales!$A$2:$F$6,4,FALSE) -> 0.037547325 | G12: =VLOOKUP(B12,Umbrales!$A$2:$F$6,5,FALSE) -> 5.6564154 | H12: =VLOOKUP(B12,Umbrales!$A$2:$F$6,6,FALSE) -> 0.21790144 | I12: =IF(AND(Datos!AE12>D12,Datos!AF12>E12,Datos!AG12>F12,Datos!AS12>G12,C12<H12),1,0) -> 0 | J12: =ParticipantesCrossSectionTable[[#This Row],[dcf_fcf_gap_mm]]/ParticipantesCrossSectionTable[[#This Row],[revenue_reported_mm]] -> -0.0094337408 | K12: =VLOOKUP(B12,Umbrales!$A$2:$H$6,7,FALSE) -> 0.45222619 | L12: =VLOOKUP(B12,Umbrales!$A$2:$H$6,8,FALSE) -> 0.018748568 | M12: =IF(AND(Datos!S12>0,Datos!AH12<K12,Datos!AL12>=1,Datos!AM12<1,J12>L12),1,0) -> 0 | N12: =VLOOKUP(B12,Umbrales!$A$2:$J$6,9,FALSE) -> 0.20554363 | O12: =VLOOKUP(B12,Umbrales!$A$2:$J$6,10,FALSE) -> 0.33577849 | P12: =IF(AND(Datos!C12="Financials",Datos!AA12>N12,Datos!AD12<0,Datos!AQ12<O12),1,0) -> 0 | Q12: =VLOOKUP(B12,Umbrales!$A$2:$K$6,11,FALSE) -> 0.94867619 | R12: =IF(AND(Datos!AN12<0.85,Datos!AN12<Q12),1,0) -> 0 | S12: =1+IF(Datos!S12>0,1,0)+IF(Datos!C12="Financials",1.2,0)+1.3 -> 4.5 | T12: =(I12*1+M12*IF(Datos!S12>0,1,0)+P12*IF(Datos!C12="Financials",1,0)+R12*1.3)/S12 -> 0 | U12: =I12+M12+P12+R12 -> 0 | V12: =IF(I12=1,"Flag1 ","")&IF(M12=1,"Flag2 ","")&IF(P12=1,"Flag3 ","")&IF(R12=1,"Flag4 ","")
A13: =ParticipantesCrossSectionTable[[#This Row],[firm_id]] -> F0312 | B13: =ParticipantesCrossSectionTable[[#This Row],[sector]] -> Financials | C13: =ParticipantesCrossSectionTable[[#This Row],[fcf_reported_mm]]/ParticipantesCrossSectionTable[[#This Row],[revenue_reported_mm]] -> 0.093596707 | D13: =VLOOKUP(B13,Umbrales!$A$2:$F$6,2,FALSE) -> 0.38877435 | E13: =VLOOKUP(B13,Umbrales!$A$2:$F$6,3,FALSE) -> 0.28427196 | F13: =VLOOKUP(B13,Umbrales!$A$2:$F$6,4,FALSE) -> 0.037547325 | G13: =VLOOKUP(B13,Umbrales!$A$2:$F$6,5,FALSE) -> 5.6564154 | H13: =VLOOKUP(B13,Umbrales!$A$2:$F$6,6,FALSE) -> 0.21790144 | I13: =IF(AND(Datos!AE13>D13,Datos!AF13>E13,Datos!AG13>F13,Datos!AS13>G13,C13<H13),1,0) -> 0 | J13: =ParticipantesCrossSectionTable[[#This Row],[dcf_fcf_gap_mm]]/ParticipantesCrossSectionTable[[#This Row],[revenue_reported_mm]] -> 0.017778508 | K13: =VLOOKUP(B13,Umbrales!$A$2:$H$6,7,FALSE) -> 0.45222619 | L13: =VLOOKUP(B13,Umbrales!$A$2:$H$6,8,FALSE) -> 0.018748568 | M13: =IF(AND(Datos!S13>0,Datos!AH13<K13,Datos!AL13>=1,Datos!AM13<1,J13>L13),1,0) -> 0 | N13: =VLOOKUP(B13,Umbrales!$A$2:$J$6,9,FALSE) -> 0.20554363 | O13: =VLOOKUP(B13,Umbrales!$A$2:$J$6,10,FALSE) -> 0.33577849 | P13: =IF(AND(Datos!C13="Financials",Datos!AA13>N13,Datos!AD13<0,Datos!AQ13<O13),1,0) -> 0 | Q13: =VLOOKUP(B13,Umbrales!$A$2:$K$6,11,FALSE) -> 0.94867619 | R13: =IF(AND(Datos!AN13<0.85,Datos!AN13<Q13),1,0) -> 1 | S13: =1+IF(Datos!S13>0,1,0)+IF(Datos!C13="Financials",1.2,0)+1.3 -> 4.5 | T13: =(I13*1+M13*IF(Datos!S13>0,1,0)+P13*IF(Datos!C13="Financials",1,0)+R13*1.3)/S13 -> 0.28888889 | U13: =I13+M13+P13+R13 -> 1 | V13: =IF(I13=1,"Flag1 ","")&IF(M13=1,"Flag2 ","")&IF(P13=1,"Flag3 ","")&IF(R13=1,"Flag4 ","") -> Flag4
... A1001: =ParticipantesCrossSectionTable[[#This Row],[firm_id]] -> F0297 | B1001: =ParticipantesCrossSectionTable[[#This Row],[sector]] -> Financials | C1001: =ParticipantesCrossSectionTable[[#This Row],[fcf_reported_mm]]/ParticipantesCrossSectionTable[[#This Row],[revenue_reported_mm]] -> 0.35435895 | D1001: =VLOOKUP(B1001,Umbrales!$A$2:$F$6,2,FALSE) -> 0.38877435 | E1001: =VLOOKUP(B1001,Umbrales!$A$2:$F$6,3,FALSE) -> 0.28427196 | F1001: =VLOOKUP(B1001,Umbrales!$A$2:$F$6,4,FALSE) -> 0.037547325 | G1001: =VLOOKUP(B1001,Umbrales!$A$2:$F$6,5,FALSE) -> 5.6564154 | H1001: =VLOOKUP(B1001,Umbrales!$A$2:$F$6,6,FALSE) -> 0.21790144 | I1001: =IF(AND(Datos!AE1001>D1001,Datos!AF1001>E1001,Datos!AG1001>F1001,Datos!AS1001>G1001,C1001<H1001),1,0) -> 0 | J1001: =ParticipantesCrossSectionTable[[#This Row],[dcf_fcf_gap_mm]]/ParticipantesCrossSectionTable[[#This Row],[revenue_reported_mm]] -> -0.096562062 | K1001: =VLOOKUP(B1001,Umbrales!$A$2:$H$6,7,FALSE) -> 0.45222619 | L1001: =VLOOKUP(B1001,Umbrales!$A$2:$H$6,8,FALSE) -> 0.018748568 | M1001: =IF(AND(Datos!S1001>0,Datos!AH1001<K1001,Datos!AL1001>=1,Datos!AM1001<1,J1001>L1001),1,0) -> 0 | N1001: =VLOOKUP(B1001,Umbrales!$A$2:$J$6,9,FALSE) -> 0.20554363 | O1001: =VLOOKUP(B1001,Umbrales!$A$2:$J$6,10,FALSE) -> 0.33577849 | P1001: =IF(AND(Datos!C1001="Financials",Datos!AA1001>N1001,Datos!AD1001<0,Datos!AQ1001<O1001),1,0) -> 0 | Q1001: =VLOOKUP(B1001,Umbrales!$A$2:$K$6,11,FALSE) -> 0.94867619 | R1001: =IF(AND(Datos!AN1001<0.85,Datos!AN1001<Q1001),1,0) -> 0 | S1001: =1+IF(Datos!S1001>0,1,0)+IF(Datos!C1001="Financials",1.2,0)+1.3 -> 4.5 | T1001: =(I1001*1+M1001*IF(Datos!S1001>0,1,0)+P1001*IF(Datos!C1001="Financials",1,0)+R1001*1.3)/S1001 -> 0 | U1001: =I1001+M1001+P1001+R1001 -> 0 | V1001: =IF(I1001=1,"Flag1 ","")&IF(M1001=1,"Flag2 ","")&IF(P1001=1,"Flag3 ","")&IF(R1001=1,"Flag4 ","")
I1002: =SUM(I2:I1001) -> 1 | M1002: =SUM(M2:M1001) -> 53 | P1002: =SUM(P2:P1001) -> 12 | R1002: =SUM(R2:R1001) -> 16

Sheet Selección empresas
A1: firm_id | B1: sector | C1: fcf_margin (AI/E) | D1: percentil 75 ebitda_margin | E1: percentil 75 cfo_margin | F1: percentil 90 capex_intensity | G1: percentil 75 assets_to_revenue_x | H1: percentil 50 fcf_reported_mm/revenue_reported_mm | I1: Flag 1 capitalización gastos | J1: dcf_fcf_gap_mm / revenue_reported_mm | K1: percentil 25 maint_capex_share | L1: percentil 75 dcf_fcf_gap_mm / revenue_reported_mm | M1: Flag 2 Tipo Linn | N1: percentil 75 npl_growth_pct | O1: percentil 25 credit_loss_coverage_reported_x | P1: Flag 3 Tipo New Century | Q1: percentil 10 debt_end_to_avg_x | R1: Flag 4 Tipo Lehman | S1: Weight | T1: Red flag score | U1: Cantidad de flags activadas | V1: Flags detectadas
A2: F0086 | B2: Energy | C2: -0.10526481 | D2: 0.31196393 | E2: 0.22086835 | F2: 0.28991455 | G2: 2.8980395 | H2: -0.051192663 | I2: 0 | J2: 0.15526411 | K2: 0.58288412 | L2: 0.12091227 | M2: 1 | N2: 0 | O2: 0 | P2: 0 | Q2: 0.95246281 | R2: 1 | S2: 3.3 | T2: 0.6969697 | U2: 2 | V2: Flag2 Flag4
A3: F0027 | B3: Energy | C3: -0.081758587 | D3: 0.31196393 | E3: 0.22086835 | F3: 0.28991455 | G3: 2.8980395 | H3: -0.051192663 | I3: 1 | J3: 0.21198043 | K3: 0.58288412 | L3: 0.12091227 | M3: 1 | N3: 0 | O3: 0 | P3: 0 | Q3: 0.95246281 | R3: 0 | S3: 3.3 | T3: 0.60606061 | U3: 2 | V3: Flag1 Flag2
A4: F0870 | B4: Consumer | C4: -0.10857062 | D4: 0.18290796 | E4: 0.12205009 | F4: 0.077863509 | G4: 1.5232589 | H4: 0.031674636 | I4: 0 | J4: 0.080208952 | K4: 0.50851978 | L4: 0.060665521 | M4: 0 | N4: 0 | O4: 0 | P4: 0 | Q4: 0.94977598 | R4: 1 | S4: 2.3 | T4: 0.56521739 | U4: 1 | V4: Flag4
A5: F0550 | B5: Technology | C5: 0.072706095 | D5: 0.29147892 | E5: 0.20310035 | F5: 0.085944599 | G5: 1.6026025 | H5: 0.11012364 | I5: 0 | J5: 0.051624732 | K5: 0.41762511 | L5: 0.054196816 | M5: 0 | N5: 0 | O5: 0 | P5: 0 | Q5: 0.94630804 | R5: 1 | S5: 3.3 | T5: 0.39393939 | U5: 1 | V5: Flag4
A6: F0143 | B6: Energy | C6: 0.02757668 | D6: 0.31196393 | E6: 0.22086835 | F6: 0.28991455 | G6: 2.8980395 | H6: -0.051192663 | I6: 0 | J6: 0.056972188 | K6: 0.58288412 | L6: 0.12091227 | M6: 0 | N6: 0 | O6: 0 | P6: 0 | Q6: 0.95246281 | R6: 1 | S6: 3.3 | T6: 0.39393939 | U6: 1 | V6: Flag4
A7: F0953 | B7: Consumer | C7: 0.053035266 | D7: 0.18290796 | E7: 0.12205009 | F7: 0.077863509 | G7: 1.5232589 | H7: 0.031674636 | I7: 0 | J7: 0.037366051 | K7: 0.50851978 | L7: 0.060665521 | M7: 0 | N7: 0 | O7: 0 | P7: 0 | Q7: 0.94977598 | R7: 1 | S7: 3.3 | T7: 0.39393939 | U7: 1 | V7: Flag4
A8: F0785 | B8: Industrials | C8: -0.082862921 | D8: 0.20187193 | E8: 0.13780716 | F8: 0.14324173 | G8: 2.1323077 | H8: -0.0035903294 | I8: 0 | J8: 0.065620648 | K8: 0.50521966 | L8: 0.077995567 | M8: 0 | N8: 0 | O8: 0 | P8: 0 | Q8: 0.94976269 | R8: 1 | S8: 3.3 | T8: 0.39393939 | U8: 1 | V8: Flag4
A9: F0856 | B9: Consumer | C9: 0.02077509 | D9: 0.18290796 | E9: 0.12205009 | F9: 0.077863509 | G9: 1.5232589 | H9: 0.031674636 | I9: 0 | J9: 0.020412551 | K9: 0.50851978 | L9: 0.060665521 | M9: 0 | N9: 0 | O9: 0 | P9: 0 | Q9: 0.94977598 | R9: 1 | S9: 3.3 | T9: 0.39393939 | U9: 1 | V9: Flag4
A10: F0676 | B10: Industrials | C10: -0.09277416 | D10: 0.20187193 | E10: 0.13780716 | F10: 0.14324173 | G10: 2.1323077 | H10: -0.0035903294 | I10: 0 | J10: 0.071628414 | K10: 0.50521966 | L10: 0.077995567 | M10: 0 | N10: 0 | O10: 0 | P10: 0 | Q10: 0.94976269 | R10: 1 | S10: 3.3 | T10: 0.39393939 | U10: 1 | V10: Flag4
A11: F0647 | B11: Industrials | C11: 0.083203762 | D11: 0.20187193 | E11: 0.13780716 | F11: 0.14324173 | G11: 2.1323077 | H11: -0.0035903294 | I11: 0 | J11: 0.047559667 | K11: 0.50521966 | L11: 0.077995567 | M11: 0 | N11: 0 | O11: 0 | P11: 0 | Q11: 0.94976269 | R11: 1 | S11: 3.3 | T11: 0.39393939 | U11: 1 | V11: Flag4
A12: F0036 | B12: Energy | C12: -0.005416753 | D12: 0.31196393 | E12: 0.22086835 | F12: 0.28991455 | G12: 2.8980395 | H12: -0.051192663 | I12: 0 | J12: 0.055959935 | K12: 0.58288412 | L12: 0.12091227 | M12: 0 | N12: 0 | O12: 0 | P12: 0 | Q12: 0.95246281 | R12: 1 | S12: 3.3 | T12: 0.39393939 | U12: 1 | V12: Flag4
A13: F0619 | B13: Industrials | C13: -0.026541934 | D13: 0.20187193 | E13: 0.13780716 | F13: 0.14324173 | G13: 2.1323077 | H13: -0.0035903294 | I13: 0 | J13: 0.05612161 | K13: 0.50521966 | L13: 0.077995567 | M13: 0 | N13: 0 | O13: 0 | P13: 0 | Q13: 0.94976269 | R13: 1 | S13: 3.3 | T13: 0.39393939 | U13: 1 | V13: Flag4
... A81: F0384 | B81: Financials | C81: 0.2173331 | D81: 0.38877435 | E81: 0.28427196 | F81: 0.037547325 | G81: 5.6564154 | H81: 0.21790144 | I81: 0 | J81: -0.12403017 | K81: 0.45222619 | L81: 0.018748568 | M81: 0 | N81: 0.20554363 | O81: 0.33577849 | P81: 1 | Q81: 0.94867619 | R81: 0 | S81: 4.5 | T81: 0.22222222 | U81: 1 | V81: Flag3
A82: F0902 | B82: Consumer | C82: 0.094675636 | D82: 0.18290796 | E82: 0.12205009 | F82: 0.077863509 | G82: 1.5232589 | H82: 0.031674636 | I82: 0 | J82: 0.021064762 | K82: 0.50851978 | L82: 0.060665521 | M82: 0 | N82: 0 | O82: 0 | P82: 0 | Q82: 0.94977598 | R82: 0 | S82: 3.3 | T82: 0 | U82: 0
A83: F0433 | B83: Technology | C83: 0.12246621 | D83: 0.29147892 | E83: 0.20310035 | F83: 0.085944599 | G83: 1.6026025 | H83: 0.11012364 | I83: 0 | J83: 0.077214941 | K83: 0.41762511 | L83: 0.054196816 | M83: 0 | N83: 0 | O83: 0 | P83: 0 | Q83: 0.94630804 | R83: 0 | S83: 3.3 | T83: 0 | U83: 0
A84: F0060 | B84: Energy | C84: -0.0024173841 | D84: 0.31196393 | E84: 0.22086835 | F84: 0.28991455 | G84: 2.8980395 | H84: -0.051192663 | I84: 0 | J84: 0.060429955 | K84: 0.58288412 | L84: 0.12091227 | M84: 0 | N84: 0 | O84: 0 | P84: 0 | Q84: 0.95246281 | R84: 0 | S84: 3.3 | T84: 0 | U84: 0
A85: F0257 | B85: Financials | C85: 0.155931 | D85: 0.38877435 | E85: 0.28427196 | F85: 0.037547325 | G85: 5.6564154 | H85: 0.21790144 | I85: 0 | J85: 0.057049236 | K85: 0.45222619 | L85: 0.018748568 | M85: 0 | N85: 0.20554363 | O85: 0.33577849 | P85: 0 | Q85: 0.94867619 | R85: 0 | S85: 4.5 | T85: 0 | U85: 0
A86: F0057 | B86: Energy | C86: 0.013002452 | D86: 0.31196393 | E86: 0.22086835 | F86: 0.28991455 | G86: 2.8980395 | H86: -0.051192663 | I86: 0 | J86: 0.049680118 | K86: 0.58288412 | L86: 0.12091227 | M86: 0 | N86: 0 | O86: 0 | P86: 0 | Q86: 0.95246281 | R86: 0 | S86: 3.3 | T86: 0 | U86: 0
A87: F0657 | B87: Industrials | C87: 0.0059857745 | D87: 0.20187193 | E87: 0.13780716 | F87: 0.14324173 | G87: 2.1323077 | H87: -0.0035903294 | I87: 0 | J87: 0.024638073 | K87: 0.50521966 | L87: 0.077995567 | M87: 0 | N87: 0 | O87: 0 | P87: 0 | Q87: 0.94976269 | R87: 0 | S87: 3.3 | T87: 0 | U87: 0
A88: F0773 | B88: Industrials | C88: 0.12293248 | D88: 0.20187193 | E88: 0.13780716 | F88: 0.14324173 | G88: 2.1323077 | H88: -0.0035903294 | I88: 0 | J88: 0.021090542 | K88: 0.50521966 | L88: 0.077995567 | M88: 0 | N88: 0 | O88: 0 | P88: 0 | Q88: 0.94976269 | R88: 0 | S88: 3.3 | T88: 0 | U88: 0
A89: F0574 | B89: Technology | C89: 0.044205475 | D89: 0.29147892 | E89: 0.20310035 | F89: 0.085944599 | G89: 1.6026025 | H89: 0.11012364 | I89: 0 | J89: 0.07443085 | K89: 0.41762511 | L89: 0.054196816 | M89: 0 | N89: 0 | O89: 0 | P89: 0 | Q89: 0.94630804 | R89: 0 | S89: 3.3 | T89: 0 | U89: 0
A90: F0438 | B90: Technology | C90: 0.091195038 | D90: 0.29147892 | E90: 0.20310035 | F90: 0.085944599 | G90: 1.6026025 | H90: 0.11012364 | I90: 0 | J90: 0.039467969 | K90: 0.41762511 | L90: 0.054196816 | M90: 0 | N90: 0 | O90: 0 | P90: 0 | Q90: 0.94630804 | R90: 0 | S90: 3.3 | T90: 0 | U90: 0
A91: F0375 | B91: Financials | C91: 0.20711459 | D91: 0.38877435 | E91: 0.28427196 | F91: 0.037547325 | G91: 5.6564154 | H91: 0.21790144 | I91: 0 | J91: -0.0067471496 | K91: 0.45222619 | L91: 0.018748568 | M91: 0 | N91: 0.20554363 | O91: 0.33577849 | P91: 0 | Q91: 0.94867619 | R91: 0 | S91: 4.5 | T91: 0 | U91: 0
A92: F0296 | B92: Financials | C92: 0.28279999 | D92: 0.38877435 | E92: 0.28427196 | F92: 0.037547325 | G92: 5.6564154 | H92: 0.21790144 | I92: 0 | J92: -0.0094337408 | K92: 0.45222619 | L92: 0.018748568 | M92: 0 | N92: 0.20554363 | O92: 0.33577849 | P92: 0 | Q92: 0.94867619 | R92: 0 | S92: 4.5 | T92: 0 | U92: 0
A93: F0808 | B93: Consumer | C93: -0.047648303 | D93: 0.18290796 | E93: 0.12205009 | F93: 0.077863509 | G93: 1.5232589 | H93: 0.031674636 | I93: 0 | J93: 0.057740051 | K93: 0.50851978 | L93: 0.060665521 | M93: 0 | N93: 0 | O93: 0 | P93: 0 | Q93: 0.94977598 | R93: 0 | S93: 3.3 | T93: 0 | U93: 0
... A1001: F0297 | B1001: Financials | C1001: 0.35435895 | D1001: 0.38877435 | E1001: 0.28427196 | F1001: 0.037547325 | G1001: 5.6564154 | H1001: 0.21790144 | I1001: 0 | J1001: -0.096562062 | K1001: 0.45222619 | L1001: 0.018748568 | M1001: 0 | N1001: 0.20554363 | O1001: 0.33577849 | P1001: 0 | Q1001: 0.94867619 | R1001: 0 | S1001: 4.5 | T1001: 0 | U1001: 0

Sheet Diccionario
A1: Variable | B1: Descripción
A2: firm_id | B2: Identificador único de la empresa. Tratar como identificador, no como predictor.
A3: firm_name | B3: Nombre ficticio de la empresa. Tratar como identificador.
A4: sector | B4: Sector económico simulado.
A5: reporting_period | B5: Período común de análisis. Es constante en toda la base.
A6: revenue_reported_mm | B6: Ingresos reportados, en millones.
A7: revenue_growth_pct | B7: Crecimiento de ingresos respecto del período previo, ya calculado.
A8: operating_expenses_reported_mm | B8: Gastos operativos reportados, en millones.
A9: ebitda_reported_mm | B9: EBITDA reportado, en millones.
A10: ebitda_margin_change_pp | B10: Cambio del margen EBITDA respecto del período previo, en puntos porcentuales.
A11: cfo_reported_mm | B11: Flujo de caja operativo reportado, en millones.
A12: capex_total_reported_mm | B12: Capex total reportado, en millones.
... A46: assets_to_revenue_x | B46: Activos reportados divididos ingresos reportados.

Sheet Información
A1: DATASET SINTÉTICO DE FINANCIAL SHENANIGANS
A2: Unidad de observación | B2: Una empresa en un único período de análisis.
A3: Cantidad de observaciones | B3: 1.000 empresas.
A4: Sectores | B4: Energy, Financials, Technology, Industrials y Consumer.
A5: Unidad monetaria | B5: Millones, salvo porcentajes y ratios.
A6: Período | B6: FY2025.
A7: Naturaleza de los datos | B7: Todos los datos son sintéticos y no representan empresas reales.
A8: Objetivo | B8: Identificar señales que justifiquen una revisión financiera más profunda.
A9: Advertencia | B9: Una observación extrema o un mal desempeño no prueban la existencia de manipulación.
A10: Etiquetas | B10: Las etiquetas de evaluación se entregarán por separado para la etapa final del ejercicio.
A11: Uso de etiquetas | B11: La hoja “Etiquetas - usar al final” forma parte del mismo archivo, pero no debe utilizarse para construir las reglas ni para seleccionar variables.
A12: Integridad académica | B12: Las etiquetas se emplean únicamente en la etapa final para evaluar las alertas ya definidas.

Sheet Etiquetas - usar al final
A1: NO UTILIZAR ESTA HOJA HASTA LA SECCIÓN DE EVALUACIÓN DE LAS ALERTAS
A3: firm_id | B3: is_manipulated | C3: shenanigan_type | D3: shenanigan_name
A4: F0902 | B4: 0 | C4: 0 | D4: no_manipulation
A5: F0433 | B5: 0 | C5: 0 | D5: no_manipulation
A6: F0060 | B6: 0 | C6: 0 | D6: no_manipulation
A7: F0257 | B7: 0 | C7: 0 | D7: no_manipulation
A8: F0057 | B8: 1 | C8: 4 | D8: quarter_end_window_dressing
A9: F0657 | B9: 0 | C9: 0 | D9: no_manipulation
A10: F0773 | B10: 0 | C10: 0 | D10: no_manipulation
A11: F0574 | B11: 1 | C11: 1 | D11: expense_capitalization
A12: F0438 | B12: 0 | C12: 0 | D12: no_manipulation
A13: F0375 | B13: 0 | C13: 0 | D13: no_manipulation
A14: F0296 | B14: 0 | C14: 0 | D14: no_manipulation
A15: F0312 | B15: 1 | C15: 4 | D15: quarter_end_window_dressing
... A1003: F0297 | B1003: 0 | C1003: 0 | D1003: no_manipulation
